[
    {
        "id": 1,
        "model_name": "word2vec_2.model",
        "window": 1,
        "vector_size": 200,
        "marks": [
            0,
            1,
            1,
            6,
            0,
            5,
            8,
            8,
            8,
            0
        ],
        "accuracy": 53.75
    },
    {
        "id": 2,
        "model_name": "fasttext_7.model",
        "window": 4,
        "vector_size": 500,
        "marks": [
            0,
            3,
            8,
            3,
            0,
            8,
            8,
            4,
            8,
            8
        ],
        "accuracy": 37.5
    },
    {
        "id": 3,
        "model_name": "fasttext_1.model",
        "window": 1,
        "vector_size": 200,
        "marks": [
            0,
            3,
            8,
            0,
            0,
            8,
            8,
            8,
            8,
            5
        ],
        "accuracy": 40.0
    },
    {
        "id": 4,
        "model_name": "word2vec_4.model",
        "window": 4,
        "vector_size": 200,
        "marks": [
            0,
            1,
            0,
            0,
            0,
            8,
            8,
            0,
            1,
            0
        ],
        "accuracy": 77.5
    },
    {
        "id": 5,
        "model_name": "word2vec_6.model",
        "window": 1,
        "vector_size": 500,
        "marks": [
            0,
            1,
            0,
            0,
            0,
            4,
            8,
            4,
            8,
            0
        ],
        "accuracy": 68.75
    },
    {
        "id": 6,
        "model_name": "word2vec_8.model",
        "window": 4,
        "vector_size": 500,
        "marks": [
            0,
            1,
            0,
            0,
            0,
            5,
            6,
            0,
            2,
            0
        ],
        "accuracy": 82.5
    },
    {
        "id": 7,
        "model_name": "fasttext_3.model",
        "window": 4,
        "vector_size": 200,
        "marks": [
            0,
            3,
            8,
            4,
            0,
            8,
            8,
            3,
            8,
            7
        ],
        "accuracy": 38.75
    },
    {
        "id": 8,
        "model_name": "fasttext_5.model",
        "window": 1,
        "vector_size": 500,
        "marks": [
            0,
            3,
            8,
            1,
            0,
            8,
            8,
            8,
            8,
            8
        ],
        "accuracy": 35.0
    }
]